zeeq/__init__.py
zeeq/interpreter.py
zeeq-1.1.4.dist-info/METADATA
zeeq-1.1.4.dist-info/WHEEL
zeeq-1.1.4.dist-info/top_level.txt
zeeq-1.1.4.dist-info/RECORD
