Metadata-Version: 2.2
Name: zeeq
Version: 1.1.4
Summary: A natural language interface for quantum programming using Cirq.
Home-page: https://github.com/athish-ns/zeeq
Author: Athish NS
Author-email: athishnsofficial@gmail.com
License: MIT
Classifier: Programming Language :: Python :: 3
Classifier: License :: OSI Approved :: MIT License
Classifier: Operating System :: OS Independent
Classifier: Topic :: Scientific/Engineering :: Physics
Requires-Python: >=3.7
Requires-Dist: cirq
Requires-Dist: numpy
Requires-Dist: logging
Requires-Dist: matplotlib
Dynamic: author
Dynamic: author-email
Dynamic: classifier
Dynamic: description
Dynamic: description-content-type
Dynamic: home-page
Dynamic: license
Dynamic: requires-dist
Dynamic: requires-python
Dynamic: summary
